Workbook
Name APORTE: 'FERRAMENTA '!$D$10
Name QTD_ANOS: 'FERRAMENTA '!$D$11:$D$11
Name RENDIMENTO_CARTEIRA: 'FERRAMENTA '!$D$6:$D$6
Name SALARIO: 'FERRAMENTA '!$D$5:$D$5
Name TAXA_MENSAL: 'FERRAMENTA '!$D$12:$D$12

Sheet FERRAMENTA 
A1: APP DE CONTROLE DE INVESTIMENTOS
B4: CONFIGURAÇÕES
B5: SALÁRIO | D5: 1620
B6: RENDIMENTO CARTEIRA | D6: 0.0108
B7: INVESTIMENTO SUGERIDO | D7: {=SALARIO*30%} -> 486
B9: INVESTIMENTO MENSAL
B10: VALOR | D10: 100
B11: NÚMERO DE ANOS | D11: 5
B12: TAXA DE RENDIMENTO | D12: 0.01079
B13: PATRIMÔNIO ACUMULADO | D13: {=FV(TAXA_MENSAL,QTD_ANOS*12,APORTE*-1)} -> 8377.6914
B14: DIVIDENDOS MENSAIS | D14: =D13*$D$6 -> 90.479067
B16: CENÁRIOS | D16: DIVIDENDOS
B17: RENDIMENTO EM 2 ANOS | C17: {=FV(TAXA_MENSAL,2*12,-APORTE)} -> 2722.7627 | D17: {=C17*RENDIMENTO_CARTEIRA} -> 29.405837
B18: RENDIMENTO EM 5 ANOS | C18: {=FV(TAXA_MENSAL,5*12,-APORTE)} -> 8377.6914 | D18: {=C18*RENDIMENTO_CARTEIRA} -> 90.479067
B19: RENDIMENTO EM 10 ANOS | C19: {=FV(TAXA_MENSAL,10*12,-APORTE)} -> 24328.421 | D19: {=C19*RENDIMENTO_CARTEIRA} -> 262.74695
B20: RENDIMENTO EM 20 ANOS | C20: {=FV(TAXA_MENSAL,20*12,-APORTE)} -> 112519.84 | D20: {=C20*RENDIMENTO_CARTEIRA} -> 1215.2143
B21: RENDIMENTO EM 30 ANOS | C21: {=FV(TAXA_MENSAL,30*12,-APORTE)} -> 432216.97 | D21: {=C21*RENDIMENTO_CARTEIRA} -> 4667.9432
B23: PERFIL | C23: AGRESSIVO
B24: VALOR DE INVESTIMENTO MENSAL | C24: =APORTE -> 100
B26: TIPOS DE FII | C26: PERCENTUAL SUGERIDO | D26: VALORES
B27: PAPEL | C27: =VLOOKUP($C$23&"-"&B27,CHAVES!A2:$D$24,4,FALSE) -> 0.5 | D27: =C27*$C$24 -> 50
B28: TIJOLO | C28: =VLOOKUP($C$23&"-"&B28,CHAVES!A3:$D$24,4,FALSE) -> 0.1 | D28: =C28*$C$24 -> 10
B29: HIBRIDOS | C29: =VLOOKUP($C$23&"-"&B29,CHAVES!A4:$D$24,4,FALSE) -> 0.05 | D29: =C29*$C$24 -> 5
B30: FOFs | C30: =VLOOKUP($C$23&"-"&B30,CHAVES!A5:$D$24,4,FALSE) -> 0.05 | D30: =C30*$C$24 -> 5
B31: HOTELARIA | C31: =VLOOKUP($C$23&"-"&B31,CHAVES!A6:$D$24,4,FALSE) -> 0.2 | D31: =C31*$C$24 -> 20
B32: DESENVOLVIMENTO | C32: =VLOOKUP($C$23&"-"&B32,CHAVES!A7:$D$24,4,FALSE) -> 0.1 | D32: =C32*$C$24 -> 10

Sheet CHAVES
A2: CHAVE | B2: PERFIL | C2: TIPOS DE FIIs | D2: PERCENTUAL
A3: CONSERVADOR-PAPEL | B3: CONSERVADOR | C3: PAPEL | D3: 0.3
A4: CONSERVADOR-TIJOLO | B4: CONSERVADOR | C4: TIJOLO | D4: 0.5
A5: CONSERVADOR-HIBRIDOS | B5: CONSERVADOR | C5: HIBRIDOS | D5: 0.1
A6: CONSERVADOR-FOFs | B6: CONSERVADOR | C6: FOFs | D6: 0.1
A7: CONSERVADOR-HOTELARIA | B7: CONSERVADOR | C7: HOTELARIA | D7: 0
A8: CONSERVADOR-DESENVOLVIMENTO | B8: CONSERVADOR | C8: DESENVOLVIMENTO | D8: 0
A10: CHAVE | B10: PERFIL | C10: TIPOS DE FIIs | D10: PERCENTUAL
A11: MODERADO-PAPEL | B11: MODERADO | C11: PAPEL | D11: 0.32
A12: MODERADO-TIJOLO | B12: MODERADO | C12: TIJOLO | D12: 0.4
A13: MODERADO-HIBRIDOS | B13: MODERADO | C13: HIBRIDOS | D13: 0.13
A14: MODERADO-FOFs | B14: MODERADO | C14: FOFs | D14: 0.05
A15: MODERADO-HOTELARIA | B15: MODERADO | C15: HOTELARIA | D15: 0.05
A16: MODERADO-DESENVOLVIMENTO | B16: MODERADO | C16: DESENVOLVIMENTO | D16: 0.05
A18: CHAVE | B18: PERFIL | C18: TIPOS DE FIIs | D18: PERCENTUAL
A19: AGRESSIVO-PAPEL | B19: AGRESSIVO | C19: PAPEL | D19: 0.5
A20: AGRESSIVO-TIJOLO | B20: AGRESSIVO | C20: TIJOLO | D20: 0.1
A21: AGRESSIVO-HIBRIDOS | B21: AGRESSIVO | C21: HIBRIDOS | D21: 0.05
A22: AGRESSIVO-FOFs | B22: AGRESSIVO | C22: FOFs | D22: 0.05
A23: AGRESSIVO-HOTELARIA | B23: AGRESSIVO | C23: HOTELARIA | D23: 0.2
A24: AGRESSIVO-DESENVOLVIMENTO | B24: AGRESSIVO | C24: DESENVOLVIMENTO | D24: 0.1
